addresskr/__init__.py
addresskr/jusogokr.py
addresskr/법정동코드 전체자료.txt
addresskr-0.1.4.dist-info/licenses/LICENSE
addresskr-0.1.4.dist-info/WHEEL
addresskr-0.1.4.dist-info/METADATA
addresskr-0.1.4.dist-info/RECORD
