Metadata-Version: 2.4
Name: addresskr
Version: 0.1.4
Summary: Parse Korean address text into various address fields based on juso.go.kr API
Author-email: Pak Youngrok <youngrok@finecode.kr>
Classifier: Development Status :: 4 - Beta
Classifier: License :: OSI Approved :: Apache Software License
License-File: LICENSE
Requires-Dist: requests
Requires-Dist: typer
Requires-Dist: ipython
Requires-Dist: python-dotenv
Project-URL: Documentation, https://github.com/finecodekr/addresskr
Project-URL: Home, https://github.com/finecodekr/addresskr
